detect_row/__init__.py
detect_row/advanced_column_extractor.py
detect_row/advanced_row_extractor.py
detect_row/advanced_table_extractor.py
detect_row/base.py
detect_row/basic_row_extractor.py
detect_row/enhanced_column_detector.py
detect_row/gpu_support.py
detect_row/tesseract_ocr_extractor.py
detect_row-2.0.5.dist-info/licenses/LICENSE
detect_row-2.0.5.dist-info/METADATA
detect_row-2.0.5.dist-info/WHEEL
detect_row-2.0.5.dist-info/entry_points.txt
detect_row-2.0.5.dist-info/top_level.txt
detect_row-2.0.5.dist-info/RECORD
