Metadata-Version: 2.4
Name: detect-row
Version: 2.0.5
Summary: Hệ thống trích xuất bảng, hàng, cột hoàn chỉnh với AI và GPU support
Home-page: https://github.com/detectrow/detect-row
Author: AI Assistant & Row Detection Team
Author-email: AI Assistant & Row Detection Team <detect.row.team@gmail.com>
Maintainer-email: AI Assistant <ai.assistant@detectrow.com>
License: MIT
Project-URL: Homepage, https://github.com/detectrow/detect-row
Project-URL: Documentation, https://github.com/detectrow/detect-row/blob/main/COMPLETE_USAGE_GUIDE.md
Project-URL: Quick Guide, https://github.com/detectrow/detect-row/blob/main/HUONG_DAN_NHANH.md
Project-URL: Vietnamese Guide, https://github.com/detectrow/detect-row/blob/main/HUONG_DAN_SU_DUNG.md
Project-URL: Repository, https://github.com/detectrow/detect-row
Project-URL: Bug Reports, https://github.com/detectrow/detect-row/issues
Project-URL: Changelog, https://github.com/detectrow/detect-row/blob/main/CHANGELOG.md
Keywords: computer vision,table extraction,row detection,column extraction,OCR,vietnamese,image processing,AI,GPU,machine learning,document processing,automated extraction
Platform: any
Classifier: Development Status :: 5 - Production/Stable
Classifier: Intended Audience :: Developers
Classifier: Intended Audience :: Science/Research
Classifier: Intended Audience :: Information Technology
Classifier: Topic :: Scientific/Engineering :: Image Recognition
Classifier: Topic :: Scientific/Engineering :: Image Processing
Classifier: Topic :: Scientific/Engineering :: Artificial Intelligence
Classifier: Topic :: Software Development :: Libraries :: Python Modules
Classifier: Topic :: Multimedia :: Graphics :: Graphics Conversion
Classifier: License :: OSI Approved :: MIT License
Classifier: Programming Language :: Python :: 3
Classifier: Programming Language :: Python :: 3.8
Classifier: Programming Language :: Python :: 3.9
Classifier: Programming Language :: Python :: 3.10
Classifier: Programming Language :: Python :: 3.11
Classifier: Programming Language :: Python :: 3.12
Classifier: Operating System :: OS Independent
Classifier: Environment :: GPU :: NVIDIA CUDA
Classifier: Natural Language :: Vietnamese
Classifier: Natural Language :: English
Requires-Python: >=3.8
License-File: LICENSE
Requires-Dist: numpy>=1.19.0
Requires-Dist: opencv-python>=4.5.0
Requires-Dist: matplotlib>=3.4.0
Requires-Dist: pytesseract>=0.3.8
Requires-Dist: Pillow>=8.2.0
Requires-Dist: scikit-image>=0.18.0
Requires-Dist: scipy>=1.7.0
Requires-Dist: psutil>=5.8.0
Provides-Extra: gpu
Requires-Dist: torch>=1.9.0; extra == "gpu"
Requires-Dist: torchvision>=0.10.0; extra == "gpu"
Provides-Extra: dev
Requires-Dist: pytest>=6.0.0; extra == "dev"
Requires-Dist: black>=21.0.0; extra == "dev"
Requires-Dist: flake8>=3.9.0; extra == "dev"
Requires-Dist: mypy>=0.910; extra == "dev"
Provides-Extra: full
Requires-Dist: torch>=1.9.0; extra == "full"
Requires-Dist: torchvision>=0.10.0; extra == "full"
Requires-Dist: pytest>=6.0.0; extra == "full"
Requires-Dist: black>=21.0.0; extra == "full"
Requires-Dist: flake8>=3.9.0; extra == "full"
Requires-Dist: mypy>=0.910; extra == "full"
Dynamic: author
Dynamic: home-page
Dynamic: license-file
Dynamic: requires-python
